LICENSE
README.md
pyproject.toml
setup.cfg
setup.py
src/timematic/__init__.py
src/timematic/_constants.py
src/timematic/_enums.py
src/timematic/_units.py
src/timematic/_utils.py
src/timematic/constants.py
src/timematic/enums.py
src/timematic/py.typed
src/timematic/units.py
src/timematic/utils.py
src/timematic.egg-info/PKG-INFO
src/timematic.egg-info/SOURCES.txt
src/timematic.egg-info/dependency_links.txt
src/timematic.egg-info/not-zip-safe
src/timematic.egg-info/top_level.txt