Metadata-Version: 2.1
Name: timematic
Version: 0.1.1
Summary: Utilities for working with datetime.
Home-page: https://github.com/MicaelJarniac/timematic
Author: Micael Jarniac
Author-email: micael@jarniac.dev
License: MIT
Project-URL: Bug Tracker, https://github.com/MicaelJarniac/timematic/issues
Platform: UNKNOWN
Classifier: Programming Language :: Python :: 3
Classifier: Programming Language :: Python :: 3 :: Only
Classifier: License :: OSI Approved :: MIT License
Classifier: Operating System :: OS Independent
Requires-Python: >=3.6
License-File: LICENSE
